goekenstats/__init__.py
goekenstats/goekenstats.py
goekenstats-0.1.2.dist-info/licenses/LICENSE.txt
goekenstats-0.1.2.dist-info/METADATA
goekenstats-0.1.2.dist-info/WHEEL
goekenstats-0.1.2.dist-info/top_level.txt
goekenstats-0.1.2.dist-info/RECORD
