Metadata-Version: 2.4
Name: GoekenStats
Version: 0.1.2
Summary: Python package for Goeken Data Science analytics
Author-email: Ryan Goeken <your@email.com>
License: MIT
Project-URL: Homepage, https://github.com/yourusername/GoekenStats
Requires-Python: >=3.7
License-File: LICENSE.txt
Requires-Dist: pandas>=2.0
Requires-Dist: numpy>=1.26
Requires-Dist: requests>=2.32
Dynamic: license-file
